{
    "1": {
        "Opción 1": "https://ok.ru/videoembed/3868053867035",
        "Opción 2": "https://www.solidfiles.com/e/vNwGVRX2DWAPp",
        "Opción 3": "https://www.fembed.com/v/8p11pc82g-50mym",
        "Opción 4": "https://uqload.com/embed-urfx0vm1tttw.html",
        "Opción 5": "https://videobin.co/embed-d989af6rjkeq.html",
        "Opción 6": "https://www.mp4upload.com/embed-hjd9rui9aqn4.html"
    },
    "2": {
        "Opción 1": "https://ok.ru/videoembed/3868057274907",
        "Opción 2": "https://www.solidfiles.com/e/eWaPznRnp328q",
        "Opción 3": "https://www.fembed.com/v/myjjyf50p1y3yjn",
        "Opción 4": "https://uqload.com/embed-u644ar17a573.html",
        "Opción 5": "https://videobin.co/embed-p7eb9m3ar3st.html",
        "Opción 6": "https://www.mp4upload.com/embed-izj3epck4u17.html"
    },
    "3": {
        "Opción 1": "https://ok.ru/videoembed/3868059634203",
        "Opción 2": "https://www.solidfiles.com/e/nkqeZDZYa78d2",
        "Opción 3": "https://www.fembed.com/v/lnjjnfn-rql-j-7",
        "Opción 4": "https://uqload.com/embed-8sq2xajnp8kc.html",
        "Opción 5": "https://videobin.co/embed-ihaa0hsv0kph.html",
        "Opción 6": "https://www.mp4upload.com/embed-qi67vmyjohod.html"
    },
    "4": {
        "Opción 1": "https://ok.ru/videoembed/3868061207067",
        "Opción 2": "https://www.solidfiles.com/e/RxmVwQW6yKmNp",
        "Opción 3": "https://www.fembed.com/v/-z22zfpezxrnekg",
        "Opción 4": "https://uqload.com/embed-wngqrnztpco3.html",
        "Opción 5": "https://videobin.co/embed-s6orutirsd2r.html",
        "Opción 6": "https://www.mp4upload.com/embed-acbnfszshoqo.html"
    },
    "5": {
        "Opción 1": "https://ok.ru/videoembed/3868064877083",
        "Opción 2": "https://www.solidfiles.com/e/3dQ5jqZ5KPNzd",
        "Opción 3": "https://www.fembed.com/v/5d00dcdpr8874mq",
        "Opción 4": "https://uqload.com/embed-33u1iz0220vh.html",
        "Opción 5": "https://videobin.co/embed-ionvmikewz7g.html",
        "Opción 6": "https://www.mp4upload.com/embed-wzi2j9stb1cv.html"
    },
    "6": {
        "Opción 1": "https://ok.ru/videoembed/3868066318875",
        "Opción 2": "https://www.solidfiles.com/e/5dyGYYMWa237G",
        "Opción 3": "https://www.fembed.com/v/60rr0t0l-ddedne",
        "Opción 4": "https://uqload.com/embed-y6nc26zk3uem.html",
        "Opción 5": "https://videobin.co/embed-n87x9yrtvqti.html",
        "Opción 6": "https://www.mp4upload.com/embed-z8z3wte55aa1.html"
    },
    "7": {
        "Opción 1": "https://ok.ru/videoembed/3868068743707",
        "Opción 2": "https://www.solidfiles.com/e/MWqwke3pLdkNy",
        "Opción 3": "https://www.fembed.com/v/x4kk4b5lnzz2y36",
        "Opción 4": "https://uqload.com/embed-w1yw2wf5q74u.html",
        "Opción 5": "https://videobin.co/embed-o7sdz2z327fr.html",
        "Opción 6": "https://www.mp4upload.com/embed-yr8sug896omg.html"
    },
    "8": {
        "Opción 1": "https://ok.ru/videoembed/3868070840859",
        "Opción 2": "https://www.solidfiles.com/e/eWaPzAkAq4g2v",
        "Opción 3": "https://www.fembed.com/v/j-jj-ad-700567d",
        "Opción 4": "https://uqload.com/embed-ksahqb1ymb4f.html",
        "Opción 5": "https://videobin.co/embed-8951tho4z9ez.html",
        "Opción 6": "https://www.mp4upload.com/embed-0ei3grmdgtnf.html"
    },
    "9": {
        "Opción 1": "https://ok.ru/videoembed/3868073396763",
        "Opción 2": "https://www.solidfiles.com/e/vNwGQWM6V3jLr",
        "Opción 3": "https://www.fembed.com/v/j-jj-ad-7004y63",
        "Opción 4": "https://uqload.com/embed-4htlv94spcni.html",
        "Opción 5": "https://videobin.co/embed-dhzr8zcl12zx.html",
        "Opción 6": "https://www.mp4upload.com/embed-jgsw35slk8m1.html"
    },
    "10": {
        "Opción 1": "https://ok.ru/videoembed/3868074773019",
        "Opción 2": "https://www.solidfiles.com/e/DeaA7DYXD65d6",
        "Opción 3": "https://www.fembed.com/v/nyjjyf2gzlln7nx",
        "Opción 4": "https://uqload.com/embed-lx0hiz3t17ow.html",
        "Opción 5": "https://videobin.co/embed-gwz5n7ml5f6p.html",
        "Opción 6": "https://www.mp4upload.com/embed-w81nc5pwibwz.html"
    },
    "11": {
        "Opción 1": "https://ok.ru/videoembed/3868076542491",
        "Opción 2": "https://www.solidfiles.com/e/y6XV7xeYVQWYz",
        "Opción 3": "https://www.fembed.com/v/x4kk4b5lnzz0yr-",
        "Opción 4": "https://uqload.com/embed-soc5q45s6cje.html",
        "Opción 5": "https://videobin.co/embed-r9wf98sfzp3r.html",
        "Opción 6": "https://www.mp4upload.com/embed-y51of74btp8f.html"
    },
    "12": {
        "Opción 1": "https://ok.ru/videoembed/3868077984283",
        "Opción 2": "https://www.solidfiles.com/e/2d43nXmAa53ZW",
        "Opción 3": "https://www.fembed.com/v/kyjjyf3kdyly3kn",
        "Opción 4": "https://uqload.com/embed-taka7dptsoa2.html",
        "Opción 5": "https://videobin.co/embed-hcuu60vn7rfn.html",
        "Opción 6": "https://www.mp4upload.com/embed-56w5ro6grxbk.html"
    }
}