{
    "1": {
        "Opción 1": "https://ok.ru/videoembed/1416722188893",
        "Opción 2": "https://www.fembed.com/v/gqjjqc-myj7dwkz",
        "Opción 3": "https://uqload.com/embed-7kmeqkidv2xt.html",
        "Opción 4": "https://videobin.co/embed-1e6ieh0o4zp5.html",
        "Opción 5": "https://www.mp4upload.com/embed-nvzlogzuq8c6.html"
    },
    "2": {
        "Opción 1": "https://ok.ru/videoembed/1416724417117",
        "Opción 2": "https://www.fembed.com/v/7rpprtgxq4-6p1d",
        "Opción 3": "https://uqload.com/embed-bfn814gnic9m.html",
        "Opción 4": "https://videobin.co/embed-0m9xsayxdqe0.html",
        "Opción 5": "https://www.mp4upload.com/embed-08s2all9spmz.html"
    },
    "3": {
        "Opción 1": "https://ok.ru/videoembed/1416728152669",
        "Opción 2": "https://www.fembed.com/v/myjjyf583ydr54j",
        "Opción 3": "https://uqload.com/embed-sww4mj5qhbo5.html",
        "Opción 4": "https://videobin.co/embed-1ytn4er0cf06.html",
        "Opción 5": "https://www.mp4upload.com/embed-kcn6jpbqama9.html"
    },
    "4": {
        "Opción 1": "https://ok.ru/videoembed/1416739424861",
        "Opción 2": "https://www.fembed.com/v/ry77yfem-2xzznx",
        "Opción 3": "https://uqload.com/embed-3mxw17hqzltf.html",
        "Opción 4": "https://videobin.co/embed-sckn1s7rqq2r.html",
        "Opción 5": "https://www.mp4upload.com/embed-yqo6kevhjmds.html"
    },
    "5": {
        "Opción 1": "https://ok.ru/videoembed/1416741259869",
        "Opción 2": "https://www.fembed.com/v/lnjjnfndwl46e6j",
        "Opción 3": "https://uqload.com/embed-f2pfzchsg3bq.html",
        "Opción 4": "https://videobin.co/embed-167zutld2mel.html",
        "Opción 5": "https://www.mp4upload.com/embed-9oinytlrr2yd.html"
    },
    "6": {
        "Opción 1": "https://ok.ru/videoembed/1416744208989",
        "Opción 2": "https://www.fembed.com/v/dkjjktxj5m343yl",
        "Opción 3": "https://uqload.com/embed-ozx7l20b7kjk.html",
        "Opción 4": "https://videobin.co/embed-ztzgjl42qmcq.html",
        "Opción 5": "https://www.mp4upload.com/embed-unr1wvqk9s53.html"
    },
    "7": {
        "Opción 1": "https://ok.ru/videoembed/1416746961501",
        "Opción 2": "https://www.fembed.com/v/24664b2pl8g3-03",
        "Opción 3": "https://uqload.com/embed-o6jshcspcez2.html",
        "Opción 4": "https://videobin.co/embed-ktd8t1kqzcts.html",
        "Opción 5": "https://www.mp4upload.com/embed-4tgzwje7pt0r.html"
    },
    "8": {
        "Opción 1": "https://ok.ru/videoembed/1416751876701",
        "Opción 2": "https://www.fembed.com/v/z7mm7ujr6m752yj",
        "Opción 3": "https://uqload.com/embed-e26q5hggfm9m.html",
        "Opción 4": "https://videobin.co/embed-7l6dre6pk9gt.html",
        "Opción 5": "https://www.mp4upload.com/embed-pv92co2npkqu.html"
    },
    "9": {
        "Opción 1": "https://ok.ru/videoembed/1416753908317",
        "Opción 2": "https://www.fembed.com/v/e2jj2c-1lrye1zz",
        "Opción 3": "https://uqload.com/embed-wsi4r9uqmmjk.html",
        "Opción 4": "https://videobin.co/embed-vl40gavrvj6u.html",
        "Opción 5": "https://www.mp4upload.com/embed-hygv4mvi47vk.html"
    },
    "10": {
        "Opción 1": "https://ok.ru/videoembed/1416756333149",
        "Opción 2": "https://www.fembed.com/v/ry77yfem-124x2w",
        "Opción 3": "https://uqload.com/embed-mkcp2jejnng1.html",
        "Opción 4": "https://videobin.co/embed-te728agnkcz3.html",
        "Opción 5": "https://www.mp4upload.com/embed-6a2dtc7b6z7z.html"
    },
    "11": {
        "Opción 1": "https://ok.ru/videoembed/1416758954589",
        "Opción 2": "https://www.fembed.com/v/myjjyf5831yk0mn",
        "Opción 3": "https://uqload.com/embed-vi275dp2rmkp.html",
        "Opción 4": "https://videobin.co/embed-q91l705tg8la.html",
        "Opción 5": "https://www.mp4upload.com/embed-1yf26j87gom8.html"
    },
    "12": {
        "Opción 1": "https://ok.ru/videoembed/1416766425693",
        "Opción 2": "https://www.fembed.com/v/8p11pc8rl--wgxr",
        "Opción 3": "https://uqload.com/embed-p22kid0uvkzm.html",
        "Opción 4": "https://videobin.co/embed-fu3ru5w94d5e.html",
        "Opción 5": "https://www.mp4upload.com/embed-lej8dkscs3yv.html"
    },
    "13": {
        "Opción 1": "https://ok.ru/videoembed/1416773241437",
        "Opción 2": "https://www.fembed.com/v/w3113an-j00gmwy",
        "Opción 3": "https://uqload.com/embed-hs3dheug3nq7.html",
        "Opción 4": "https://videobin.co/embed-iflzicwql79e.html",
        "Opción 5": "https://www.mp4upload.com/embed-n141z1kktkcj.html"
    }
}