{
    "1": {
        "Opción 1": "https://ok.ru/videoembed/1628186151526",
        "Opción 2": "https://drive.google.com/file/d/1o2bizPfbgh8E_EICQ5W43UVrtKX5pNs8/preview",
        "Opción 3": "https://www.mp4upload.com/embed-vouz6xdij8uc.html",
        "Opción 4": "https://uqload.com/embed-skr5in1pzntw.html",
        "Opción 5": "https://repro.monoschinos2.com/aqua/sv?url=https://sendvid.com/otvhqng0"
    },
    "2": {
        "Opción 1": "https://ok.ru/videoembed/1628187134566",
        "Opción 2": "https://drive.google.com/file/d/1Qc9R2MILq5Gxj6ssEUclgJ7sF_OxLcsN/preview",
        "Opción 3": "https://www.mp4upload.com/embed-hrcykk4tbb5d.html",
        "Opción 4": "https://uqload.com/embed-yocj089hl5ri.html",
        "Opción 5": "https://repro.monoschinos2.com/aqua/sv?url=https://sendvid.com/3fnv0fi0"
    },
    "3": {
        "Opción 1": "https://ok.ru/videoembed/1628187986534",
        "Opción 2": "https://drive.google.com/file/d/1CKtNqO-KoJPqYOJugotrEcMsdOPixVfS/preview",
        "Opción 3": "https://www.mp4upload.com/embed-ht5o4kpossux.html",
        "Opción 4": "https://uqload.com/embed-a14gl702fpef.html",
        "Opción 5": "https://repro.monoschinos2.com/aqua/sv?url=https://sendvid.com/4wqdqhe5"
    },
    "4": {
        "Opción 1": "https://ok.ru/videoembed/1628188641894",
        "Opción 2": "https://drive.google.com/file/d/1kKx_BtQA68-b39e1yyNPZaOGMhO4kRhj/preview",
        "Opción 3": "https://www.mp4upload.com/embed-z6p9i4d3xk71.html",
        "Opción 4": "https://uqload.com/embed-wcx96vhjqnsi.html",
        "Opción 5": "https://repro.monoschinos2.com/aqua/sv?url=https://sendvid.com/cav8n1j4"
    },
    "5": {
        "Opción 1": "https://ok.ru/videoembed/1628189493862",
        "Opción 2": "https://drive.google.com/file/d/11jIOmatXQHVauTD6N8kh7spqSymq4GLi/preview",
        "Opción 3": "https://www.mp4upload.com/embed-jhsvz68vu2y6.html",
        "Opción 4": "https://uqload.com/embed-danklqix2a5v.html",
        "Opción 5": "https://repro.monoschinos2.com/aqua/sv?url=https://sendvid.com/qvuvia9k",
        "Opción 6": "https://vidlox.me/embed-jtv7ez1vat32"
    },
    "6": {
        "Opción 1": "https://ok.ru/videoembed/1628190018150",
        "Opción 2": "https://drive.google.com/file/d/1A0fFjXm28aIMhSj5O-a0ZSvYBvKoEyAj/preview",
        "Opción 3": "https://www.mp4upload.com/embed-lbkqx4z3n1dn.html",
        "Opción 4": "https://uqload.com/embed-jm2kky1iaylc.html",
        "Opción 5": "https://repro.monoschinos2.com/aqua/sv?url=https://sendvid.com/yhf7bms1",
        "Opción 6": "https://vidlox.me/embed-zj5cqcxxm588"
    },
    "7": {
        "Opción 1": "https://ok.ru/videoembed/1628190476902",
        "Opción 2": "https://drive.google.com/file/d/1VSK2IkS2uTzb4eCOCuApEFMO7-mxpVuy/preview",
        "Opción 3": "https://www.mp4upload.com/embed-gmgz7tcsdxqz.html",
        "Opción 4": "https://uqload.com/embed-78cuvyt439u0.html",
        "Opción 5": "https://repro.monoschinos2.com/aqua/sv?url=https://sendvid.com/mzzdc3zo"
    },
    "8": {
        "Opción 1": "https://ok.ru/videoembed/1628191853158",
        "Opción 2": "https://drive.google.com/file/d/1ulFj4Kn0mmsJXXrQ2edeKLa6FakHlgYw/preview",
        "Opción 3": "https://www.mp4upload.com/embed-v0n46isbc69u.html",
        "Opción 4": "https://uqload.com/embed-97ysmedgckcy.html",
        "Opción 5": "https://repro.monoschinos2.com/aqua/sv?url=https://sendvid.com/6rdjatcs"
    },
    "9": {
        "Opción 1": "https://ok.ru/videoembed/1628192836198",
        "Opción 2": "https://drive.google.com/file/d/10720dBtxuDWmPe_tFwDiaXEws2ZY8lFy/preview",
        "Opción 3": "https://www.mp4upload.com/embed-ztbf7slzos5d.html",
        "Opción 4": "https://uqload.com/embed-46vu5pjwcpy6.html",
        "Opción 5": "https://verystream.com/e/5p618HQKq5j/Xk7okUpvGU6lc3s.mp4",
        "Opción 6": "https://repro.monoschinos2.com/aqua/sv?url=https://sendvid.com/pqwk3l4h"
    },
    "10": {
        "Opción 1": "https://ok.ru/videoembed/1628193622630",
        "Opción 2": "https://drive.google.com/file/d/1vVSB7_nOk_Cb-PqcHAyIezmZHsRotA1o/preview",
        "Opción 3": "https://www.mp4upload.com/embed-rjlsjz7ncrtp.html",
        "Opción 4": "https://uqload.com/embed-2wxg0hwzt89n.html",
        "Opción 5": "https://repro.monoschinos2.com/aqua/sv?url=https://sendvid.com/kn2pueql"
    },
    "11": {
        "Opción 1": "https://ok.ru/videoembed/1628193950310",
        "Opción 2": "https://drive.google.com/file/d/1vKgvIHufrjdD33J5geFMgG4j5r_8ZmCW/preview",
        "Opción 3": "https://www.mp4upload.com/embed-7c9lpdjmyzbo.html",
        "Opción 4": "https://uqload.com/embed-am8shjezeeiz.html",
        "Opción 5": "https://repro.monoschinos2.com/aqua/sv?url=https://sendvid.com/dz3k6qow"
    }
}