{
    "1": {
        "Opción 1": "https://ok.ru/videoembed/1893907696298",
        "Opción 2": "https://www.fembed.com/v/kyjjyf33ejqkr3q",
        "Opción 3": "https://uqload.com/embed-ohdp0ptg8l9n.html",
        "Opción 4": "https://videobin.co/embed-44ihaxidg0n8.html",
        "Opción 5": "https://www.mp4upload.com/embed-m0r1eprx0udo.html"
    },
    "2": {
        "Opción 1": "https://ok.ru/videoembed/1893909334698",
        "Opción 2": "https://www.fembed.com/v/dkjjktxxewn3dj5",
        "Opción 3": "https://uqload.com/embed-cjulien9wtfd.html",
        "Opción 4": "https://videobin.co/embed-0y73mabpcles.html",
        "Opción 5": "https://www.mp4upload.com/embed-xm3qjmvkgp08.html"
    },
    "3": {
        "Opción 1": "https://ok.ru/videoembed/1893912283818",
        "Opción 2": "https://www.fembed.com/v/5d00dcddzngg52q",
        "Opción 3": "https://uqload.com/embed-ouhl8cc8wx4y.html",
        "Opción 4": "https://videobin.co/embed-opowvvjziznu.html",
        "Opción 5": "https://www.mp4upload.com/embed-vz2i2llt9hyt.html"
    },
    "4": {
        "Opción 1": "https://ok.ru/videoembed/1893917199018",
        "Opción 2": "https://www.fembed.com/v/8p11pc880w6l86q",
        "Opción 3": "https://uqload.com/embed-5r6ihyfk2pqz.html",
        "Opción 4": "https://videobin.co/embed-1a5zmgf78i3e.html",
        "Opción 5": "https://www.mp4upload.com/embed-qdacpfdoeztg.html"
    },
    "5": {
        "Opción 1": "https://ok.ru/videoembed/1893920213674",
        "Opción 2": "https://www.fembed.com/v/05225hll-dw17kr",
        "Opción 3": "https://uqload.com/embed-lb5cc7tysebo.html",
        "Opción 4": "https://videobin.co/embed-tdbtk1ab9g3m.html",
        "Opción 5": "https://www.mp4upload.com/embed-y8jrc7qfdvpj.html"
    },
    "6": {
        "Opción 1": "https://ok.ru/videoembed/1893923228330",
        "Opción 2": "https://www.fembed.com/v/8p11pc880wzw-xz",
        "Opción 3": "https://uqload.com/embed-t8xxgadf3ng0.html",
        "Opción 4": "https://videobin.co/embed-9eeowy6w4uye.html",
        "Opción 5": "https://www.mp4upload.com/embed-vtzslrf11oz7.html"
    },
    "7": {
        "Opción 1": "https://ok.ru/videoembed/1893930175146",
        "Opción 2": "https://www.fembed.com/v/myjjyf55m4ngg07",
        "Opción 3": "https://uqload.com/embed-mtyojkoop7x2.html",
        "Opción 4": "https://videobin.co/embed-5yejfdphpy06.html",
        "Opción 5": "https://www.mp4upload.com/embed-tw6ocjeasthc.html"
    },
    "8": {
        "Opción 1": "https://ok.ru/videoembed/1893931748010",
        "Opción 2": "https://www.fembed.com/v/nyjjyf221rrzw8l",
        "Opción 3": "https://uqload.com/embed-fszluepy17sa.html",
        "Opción 4": "https://videobin.co/embed-74e5vt9khalj.html",
        "Opción 5": "https://www.mp4upload.com/embed-b23eho0vjpzg.html"
    },
    "9": {
        "Opción 1": "https://ok.ru/videoembed/1894137072298",
        "Opción 2": "https://www.fembed.com/v/nyjjyf221-k72w7",
        "Opción 3": "https://uqload.com/embed-eq4az1y87on1.html",
        "Opción 4": "https://videobin.co/embed-mroxv319ndmb.html",
        "Opción 5": "https://www.mp4upload.com/embed-l3tgye7ywo1o.html"
    },
    "10": {
        "Opción 1": "https://ok.ru/videoembed/1894138579626",
        "Opción 2": "https://www.fembed.com/v/05225hll-05gmkd",
        "Opción 3": "https://uqload.com/embed-jjusecosjb3v.html",
        "Opción 4": "https://videobin.co/embed-grgdy9se1ukt.html",
        "Opción 5": "https://www.mp4upload.com/embed-fywmih6gl7mp.html"
    },
    "11": {
        "Opción 1": "https://ok.ru/videoembed/1894139890346",
        "Opción 2": "https://www.fembed.com/v/24664b221pem8jd",
        "Opción 3": "https://uqload.com/embed-8leui2rm5tww.html",
        "Opción 4": "https://videobin.co/embed-fdnblkh48fuu.html",
        "Opción 5": "https://www.mp4upload.com/embed-fo1sfu9t03pa.html"
    },
    "12": {
        "Opción 1": "https://ok.ru/videoembed/1894140938922",
        "Opción 2": "https://www.fembed.com/v/24664b221p7gm2m",
        "Opción 3": "https://uqload.com/embed-gk9jh2x97av6.html",
        "Opción 4": "https://videobin.co/embed-biwfjac436ho.html",
        "Opción 5": "https://www.mp4upload.com/embed-ewolxeownqe0.html"
    },
    "13": {
        "Opción 1": "https://ok.ru/videoembed/1894141725354",
        "Opción 2": "https://www.fembed.com/v/z7mm7ujjdre3w86",
        "Opción 3": "https://uqload.com/embed-u4ou44mqyz6l.html",
        "Opción 4": "https://videobin.co/embed-3ajlajagi9ez.html",
        "Opción 5": "https://www.mp4upload.com/embed-rylrix8yt0wk.html"
    },
    "14": {
        "Opción 1": "https://ok.ru/videoembed/1894143167146",
        "Opción 2": "https://www.fembed.com/v/dkjjktxxej6jxq0",
        "Opción 3": "https://uqload.com/embed-hugzzg2nrf1d.html",
        "Opción 4": "https://videobin.co/embed-5vx7c8agbuar.html",
        "Opción 5": "https://www.mp4upload.com/embed-llsjdqrlrlre.html"
    },
    "15": {
        "Opción 1": "https://ok.ru/videoembed/1894144412330",
        "Opción 2": "https://www.fembed.com/v/5d00dcddzw7zgz-",
        "Opción 3": "https://uqload.com/embed-9h9f23tm9osi.html",
        "Opción 4": "https://videobin.co/embed-e23svaaabwwp.html",
        "Opción 5": "https://www.mp4upload.com/embed-shuzqn5ov9y8.html"
    },
    "16": {
        "Opción 1": "https://ok.ru/videoembed/1894145329834",
        "Opción 2": "https://www.fembed.com/v/x4kk4b55qr-wnl8",
        "Opción 3": "https://uqload.com/embed-lr3yhmcq9z6w.html",
        "Opción 4": "https://videobin.co/embed-exb1bf06du0x.html",
        "Opción 5": "https://www.mp4upload.com/embed-ekn87d5kom8n.html"
    },
    "17": {
        "Opción 1": "https://ok.ru/videoembed/1894147033770",
        "Opción 2": "https://www.fembed.com/v/gqjjqc--zm65wr4",
        "Opción 3": "https://uqload.com/embed-5d4q4q3761a6.html",
        "Opción 4": "https://videobin.co/embed-s6ywnoa757z7.html",
        "Opción 5": "https://www.mp4upload.com/embed-rslm3qushv5p.html"
    },
    "18": {
        "Opción 1": "https://ok.ru/videoembed/1894148147882",
        "Opción 2": "https://www.fembed.com/v/dkjjktxxejn3yrw",
        "Opción 3": "https://uqload.com/embed-6fsitn6r73l7.html",
        "Opción 4": "https://videobin.co/embed-vedhbayfy8tj.html",
        "Opción 5": "https://www.mp4upload.com/embed-i5wxl4kjl9h8.html"
    },
    "19": {
        "Opción 1": "https://ok.ru/videoembed/1894148737706",
        "Opción 2": "https://www.fembed.com/v/36776ammgj4zy3n",
        "Opción 3": "https://uqload.com/embed-w5ttg4lsemi3.html",
        "Opción 4": "https://videobin.co/embed-y0lwtzqufmws.html",
        "Opción 5": "https://www.mp4upload.com/embed-902jgkfritvc.html"
    },
    "20": {
        "Opción 1": "https://ok.ru/videoembed/1894150113962",
        "Opción 2": "https://www.fembed.com/v/ry77yfeezmjwe4y",
        "Opción 3": "https://uqload.com/embed-2ar10s6ilvou.html",
        "Opción 4": "https://videobin.co/embed-inkt4316rl7m.html",
        "Opción 5": "https://www.mp4upload.com/embed-qyruhvy6txeq.html"
    },
    "21": {
        "Opción 1": "https://ok.ru/videoembed/1894151359146",
        "Opción 2": "https://www.fembed.com/v/w3113annz-8m3-6",
        "Opción 3": "https://uqload.com/embed-1424yq1he7l1.html",
        "Opción 4": "https://videobin.co/embed-ogupab7tk5j2.html",
        "Opción 5": "https://www.mp4upload.com/embed-hvhaaqs6dv45.html"
    },
    "22": {
        "Opción 1": "https://ok.ru/videoembed/1894152211114",
        "Opción 2": "https://www.fembed.com/v/7rpprtgg3xyly-2",
        "Opción 3": "https://uqload.com/embed-kri7bjgti3q8.html",
        "Opción 4": "https://videobin.co/embed-s5ajfrxjb7v6.html",
        "Opción 5": "https://www.mp4upload.com/embed-i7at4ljndxsb.html"
    },
    "23": {
        "Opción 1": "https://ok.ru/videoembed/1894152669866",
        "Opción 2": "https://www.fembed.com/v/05225hll-0wzzj-",
        "Opción 3": "https://uqload.com/embed-7ygreez3addi.html",
        "Opción 4": "https://videobin.co/embed-ithmn5rgk9ke.html",
        "Opción 5": "https://www.mp4upload.com/embed-t7s69leov0dk.html"
    },
    "24": {
        "Opción 1": "https://ok.ru/videoembed/1894153915050",
        "Opción 2": "https://www.fembed.com/v/47dd7uzzejlm-e7",
        "Opción 3": "https://uqload.com/embed-z3jnxth2oz0s.html",
        "Opción 4": "https://videobin.co/embed-39boevuonlbl.html",
        "Opción 5": "https://www.mp4upload.com/embed-0oe9i66h7bje.html"
    },
    "25": {
        "Opción 1": "https://ok.ru/videoembed/1894155160234",
        "Opción 2": "https://www.fembed.com/v/j-jj-add3k1lypl",
        "Opción 3": "https://uqload.com/embed-s506eycund98.html",
        "Opción 4": "https://videobin.co/embed-d4d3m8ks3jzi.html",
        "Opción 5": "https://www.mp4upload.com/embed-m7suojknnyj4.html"
    },
    "26": {
        "Opción 1": "https://ok.ru/videoembed/1894155750058",
        "Opción 2": "https://www.fembed.com/v/dkjjktxxejqmq18",
        "Opción 3": "https://uqload.com/embed-8eetqf41olv2.html",
        "Opción 4": "https://videobin.co/embed-s1bazeo30sd4.html",
        "Opción 5": "https://www.mp4upload.com/embed-ke1v66yc7guv.html"
    },
    "27": {
        "Opción 1": "https://ok.ru/videoembed/1894156470954",
        "Opción 2": "https://www.fembed.com/v/qy66yfeej6kxl4-",
        "Opción 3": "https://uqload.com/embed-i3pd17sc18x6.html",
        "Opción 4": "https://videobin.co/embed-kn6k6bmc3qb9.html",
        "Opción 5": "https://www.mp4upload.com/embed-xb5maf3esq8s.html"
    },
    "28": {
        "Opción 1": "https://ok.ru/videoembed/1894157060778",
        "Opción 2": "https://www.fembed.com/v/lnjjnfnn3d2zz51",
        "Opción 3": "https://uqload.com/embed-816r1q9yrdqo.html",
        "Opción 4": "https://videobin.co/embed-s1vnv35t9g5b.html",
        "Opción 5": "https://www.mp4upload.com/embed-izo58rd3kf4v.html"
    },
    "29": {
        "Opción 1": "https://ok.ru/videoembed/1894157781674",
        "Opción 2": "https://www.fembed.com/v/lnjjnfnn3d2n400",
        "Opción 3": "https://uqload.com/embed-yw248prx1s1g.html",
        "Opción 4": "https://videobin.co/embed-q6e9wu0lu7r3.html",
        "Opción 5": "https://www.mp4upload.com/embed-qj9fl3804ebz.html"
    },
    "30": {
        "Opción 1": "https://ok.ru/videoembed/1894158437034",
        "Opción 2": "https://www.fembed.com/v/w3113annz-qz8y5",
        "Opción 3": "https://uqload.com/embed-ti5iglgmc5q6.html",
        "Opción 4": "https://videobin.co/embed-rzwq504phg4v.html",
        "Opción 5": "https://www.mp4upload.com/embed-sxgs9e1vn8fq.html"
    },
    "31": {
        "Opción 1": "https://ok.ru/videoembed/1894161320618",
        "Opción 2": "https://www.fembed.com/v/7rpprtgg3x5j2qj",
        "Opción 3": "https://uqload.com/embed-i1jlae56hr6d.html",
        "Opción 4": "https://videobin.co/embed-vrake3p3p2oy.html",
        "Opción 5": "https://www.mp4upload.com/embed-bvroi2q751x3.html"
    },
    "32": {
        "Opción 1": "https://ok.ru/videoembed/1894162041514",
        "Opción 2": "https://www.fembed.com/v/myjjyf55m847red",
        "Opción 3": "https://uqload.com/embed-iz9p1o72j3iu.html",
        "Opción 4": "https://videobin.co/embed-m8vtp9x5cyz8.html",
        "Opción 5": "https://www.mp4upload.com/embed-b18aoz9u0rhd.html"
    },
    "33": {
        "Opción 1": "https://ok.ru/videoembed/1894162565802",
        "Opción 2": "https://www.fembed.com/v/x4kk4b55qr3m3zw",
        "Opción 3": "https://uqload.com/embed-d0lsnx6w389f.html",
        "Opción 4": "https://videobin.co/embed-2okj3agxvhvu.html",
        "Opción 5": "https://www.mp4upload.com/embed-n8xx19ds4rfi.html"
    },
    "34": {
        "Opción 1": "https://ok.ru/videoembed/1894162893482",
        "Opción 2": "https://www.fembed.com/v/y2zz2ceepz7e32-",
        "Opción 3": "https://uqload.com/embed-go1zp0qb39mk.html",
        "Opción 4": "https://videobin.co/embed-maeuhgb9pdl9.html",
        "Opción 5": "https://www.mp4upload.com/embed-rxtcq1doyjx2.html"
    },
    "35": {
        "Opción 1": "https://ok.ru/videoembed/1894163483306",
        "Opción 2": "https://www.fembed.com/v/5d00dcddzwnzd--",
        "Opción 3": "https://uqload.com/embed-wpql6ud0eo77.html",
        "Opción 4": "https://videobin.co/embed-crfuq2ia03wk.html",
        "Opción 5": "https://www.mp4upload.com/embed-1sojb0s61zp0.html"
    },
    "36": {
        "Opción 1": "https://ok.ru/videoembed/1894163810986",
        "Opción 2": "https://www.fembed.com/v/qy66yfeej6w3e2n",
        "Opción 3": "https://uqload.com/embed-qzy23x84nlt6.html",
        "Opción 4": "https://videobin.co/embed-wwfibvivg0m2.html",
        "Opción 5": "https://www.mp4upload.com/embed-2wkzqaloq1pt.html"
    },
    "37": {
        "Opción 1": "https://ok.ru/videoembed/1894164073130",
        "Opción 2": "https://www.fembed.com/v/7rpprtgg3x5q3rn",
        "Opción 3": "https://uqload.com/embed-h939azjj6ist.html",
        "Opción 4": "https://videobin.co/embed-9s843npzv9ls.html",
        "Opción 5": "https://www.mp4upload.com/embed-3spykxoh7zqp.html"
    },
    "38": {
        "Opción 1": "https://ok.ru/videoembed/1894166301354",
        "Opción 2": "https://www.fembed.com/v/-z22zfppg52ne3z",
        "Opción 3": "https://uqload.com/embed-odt1avk4gmbc.html",
        "Opción 4": "https://videobin.co/embed-z4prbpq64zku.html",
        "Opción 5": "https://www.mp4upload.com/embed-lgbu8k46g72t.html"
    },
    "39": {
        "Opción 1": "https://ok.ru/videoembed/1894168398506",
        "Opción 2": "https://www.fembed.com/v/lnjjnfnn3dd16g5",
        "Opción 3": "https://uqload.com/embed-qvwke12g1uii.html",
        "Opción 4": "https://videobin.co/embed-lz2e102sr93h.html",
        "Opción 5": "https://www.mp4upload.com/embed-60jzwg7brke1.html"
    },
    "40": {
        "Opción 1": "https://ok.ru/videoembed/1894172527274",
        "Opción 2": "https://www.fembed.com/v/60rr0t008ee0wy8",
        "Opción 3": "https://uqload.com/embed-fx0n1g6titon.html",
        "Opción 4": "https://videobin.co/embed-a4e3lihx8bzk.html",
        "Opción 5": "https://www.mp4upload.com/embed-7m7l17f98xhf.html"
    },
    "41": {
        "Opción 1": "https://ok.ru/videoembed/1894173379242",
        "Opción 2": "https://www.fembed.com/v/47dd7uzzejj8r3y",
        "Opción 3": "https://uqload.com/embed-gz4t8iht2qe3.html",
        "Opción 4": "https://videobin.co/embed-75b3ujvk2o0a.html",
        "Opción 5": "https://www.mp4upload.com/embed-a144eaid204l.html"
    },
    "42": {
        "Opción 1": "https://ok.ru/videoembed/1894174427818",
        "Opción 2": "https://www.fembed.com/v/myjjyf55m8860re",
        "Opción 3": "https://uqload.com/embed-u2dotadrkt32.html",
        "Opción 4": "https://videobin.co/embed-hu7fc002o063.html",
        "Opción 5": "https://www.mp4upload.com/embed-5ofueug9m4ca.html"
    },
    "43": {
        "Opción 1": "https://ok.ru/videoembed/1894175017642",
        "Opción 2": "https://www.fembed.com/v/60rr0t008eew72m",
        "Opción 3": "https://uqload.com/embed-2louv3t4wv8i.html",
        "Opción 4": "https://videobin.co/embed-cis931kfc6c4.html",
        "Opción 5": "https://www.mp4upload.com/embed-nmnviuczy1qn.html"
    },
    "44": {
        "Opción 1": "https://ok.ru/videoembed/1894175869610",
        "Opción 2": "https://www.fembed.com/v/-z22zfppg55dx72",
        "Opción 3": "https://uqload.com/embed-nwmbaca999jt.html",
        "Opción 4": "https://videobin.co/embed-yw9xw8fug35u.html",
        "Opción 5": "https://www.mp4upload.com/embed-rctdszh5yavv.html"
    },
    "45": {
        "Opción 1": "https://ok.ru/videoembed/1894176918186",
        "Opción 2": "https://www.fembed.com/v/w3113annz--4xl1",
        "Opción 3": "https://uqload.com/embed-apq24js9dvrn.html",
        "Opción 4": "https://videobin.co/embed-fa894urafaet.html",
        "Opción 5": "https://www.mp4upload.com/embed-ghdxjo92xl7u.html"
    },
    "46": {
        "Opción 1": "https://ok.ru/videoembed/1894177901226",
        "Opción 2": "https://www.fembed.com/v/e2jj2c--z11j3qg",
        "Opción 3": "https://uqload.com/embed-26h8tfsfd3me.html",
        "Opción 4": "https://videobin.co/embed-o509mjjxeiur.html",
        "Opción 5": "https://www.mp4upload.com/embed-mhnp259l193f.html"
    },
    "47": {
        "Opción 1": "https://ok.ru/videoembed/1894178753194",
        "Opción 2": "https://www.fembed.com/v/z7mm7ujjdrj823d",
        "Opción 3": "https://uqload.com/embed-65f5ucg2xey5.html",
        "Opción 4": "https://videobin.co/embed-10p2153omt70.html",
        "Opción 5": "https://www.mp4upload.com/embed-51838mn3mq6e.html"
    },
    "48": {
        "Opción 1": "https://ok.ru/videoembed/1894179539626",
        "Opción 2": "https://www.fembed.com/v/z7mm7ujjdrjmgp0",
        "Opción 3": "https://uqload.com/embed-xczybnfl3xjw.html",
        "Opción 4": "https://videobin.co/embed-xtr9i2ot8dyh.html",
        "Opción 5": "https://www.mp4upload.com/embed-kv5sqbc3afo3.html"
    },
    "49": {
        "Opción 1": "https://ok.ru/videoembed/1894180194986",
        "Opción 2": "https://www.fembed.com/v/05225hll-0l51p5",
        "Opción 3": "https://uqload.com/embed-3vrlbswpm7dz.html",
        "Opción 4": "https://videobin.co/embed-ui0xvc96pe2b.html",
        "Opción 5": "https://www.mp4upload.com/embed-chubmah2xafw.html"
    },
    "50": {
        "Opción 1": "https://ok.ru/videoembed/1894180719274",
        "Opción 2": "https://www.fembed.com/v/05225hll-0lw1j7",
        "Opción 3": "https://uqload.com/embed-lp8losturt37.html",
        "Opción 4": "https://videobin.co/embed-z8qp5zlk3eri.html",
        "Opción 5": "https://www.mp4upload.com/embed-xpxyj226gtb2.html"
    },
    "51": {
        "Opción 1": "https://ok.ru/videoembed/1894181309098",
        "Opción 2": "https://www.fembed.com/v/z7mm7ujjdrj2yp7",
        "Opción 3": "https://uqload.com/embed-utx31oznrg4m.html",
        "Opción 4": "https://videobin.co/embed-9qubdg007w2e.html",
        "Opción 5": "https://www.mp4upload.com/embed-olcgfc2oom5x.html"
    }
}