{
    "1": {
        "Opción 1": "https://ok.ru/videoembed/1920290196017",
        "Opción 2": "https://www.fembed.com/v/y2zz2ce7l82k4zz",
        "Opción 3": "https://uqload.com/embed-a29qfen77ceq.html",
        "Opción 4": "https://videobin.co/embed-497rnd4hcs5j.html",
        "Opción 5": "https://www.mp4upload.com/embed-antuxtzn6pbn.html"
    },
    "2": {
        "Opción 1": "https://ok.ru/videoembed/1920290392625",
        "Opción 2": "https://www.fembed.com/v/w3113an7ky1wdmz",
        "Opción 3": "https://uqload.com/embed-fmas4q83yjoz.html",
        "Opción 4": "https://videobin.co/embed-jp2xrggx7e2c.html",
        "Opción 5": "https://www.mp4upload.com/embed-kae4ds13vym4.html"
    },
    "3": {
        "Opción 1": "https://ok.ru/videoembed/1920290654769",
        "Opción 2": "https://www.fembed.com/v/-z22zfp2n8402m2",
        "Opción 3": "https://uqload.com/embed-xj11rnb3eijv.html",
        "Opción 4": "https://videobin.co/embed-see8xyqwyfw5.html",
        "Opción 5": "https://www.mp4upload.com/embed-bwiilpzke85z.html"
    },
    "4": {
        "Opción 1": "https://ok.ru/videoembed/1920291047985",
        "Opción 2": "https://www.fembed.com/v/47dd7uzw1qgp2kj",
        "Opción 3": "https://uqload.com/embed-nr13a85tk2wm.html",
        "Opción 4": "https://videobin.co/embed-2ea0zl7lyoeg.html",
        "Opción 5": "https://www.mp4upload.com/embed-37afqv9svlrm.html"
    },
    "5": {
        "Opción 1": "https://ok.ru/videoembed/1920291441201",
        "Opción 2": "https://www.fembed.com/v/x4kk4b5367y37ng",
        "Opción 3": "https://uqload.com/embed-mjfap3r1ybvy.html",
        "Opción 4": "https://videobin.co/embed-60aspq58q3ic.html",
        "Opción 5": "https://www.mp4upload.com/embed-lqalpht3c65a.html"
    },
    "6": {
        "Opción 1": "https://ok.ru/videoembed/1920291637809",
        "Opción 2": "https://www.fembed.com/v/nyjjyf2r8nk2p55",
        "Opción 3": "https://uqload.com/embed-34rzhwt3qdkm.html",
        "Opción 4": "https://videobin.co/embed-q8kc1bgf8s4f.html",
        "Opción 5": "https://www.mp4upload.com/embed-kabi1akfbt2a.html"
    },
    "7": {
        "Opción 1": "https://ok.ru/videoembed/1920291899953",
        "Opción 2": "https://www.fembed.com/v/24664b2qzmerqw4",
        "Opción 3": "https://uqload.com/embed-bm44z0tmrn9b.html",
        "Opción 4": "https://videobin.co/embed-5plfzcsx1oha.html",
        "Opción 5": "https://www.mp4upload.com/embed-t2nzt2m7u4v6.html"
    },
    "8": {
        "Opción 1": "https://ok.ru/videoembed/1920292031025",
        "Opción 2": "https://www.fembed.com/v/-z22zfp2n84y77d",
        "Opción 3": "https://uqload.com/embed-ct6emg5aesqu.html",
        "Opción 4": "https://videobin.co/embed-5culihavno3x.html",
        "Opción 5": "https://www.mp4upload.com/embed-k5kwoj5shect.html"
    },
    "9": {
        "Opción 1": "https://ok.ru/videoembed/1920292424241",
        "Opción 2": "https://www.fembed.com/v/13443ajnl7xz7nl",
        "Opción 3": "https://uqload.com/embed-yjk44bbftxtq.html",
        "Opción 4": "https://videobin.co/embed-8hq8qgim5lhc.html",
        "Opción 5": "https://www.mp4upload.com/embed-cextrrslkf4r.html"
    },
    "10": {
        "Opción 1": "https://ok.ru/videoembed/1920292686385",
        "Opción 2": "https://www.fembed.com/v/24664b2qzmel3wq",
        "Opción 3": "https://uqload.com/embed-dcvsousueg5j.html",
        "Opción 4": "https://videobin.co/embed-qcstkj1k89g1.html",
        "Opción 5": "https://www.mp4upload.com/embed-90b777loe2rm.html"
    },
    "11": {
        "Opción 1": "https://ok.ru/videoembed/1920292948529",
        "Opción 2": "https://www.fembed.com/v/7rpprtg5017p51g",
        "Opción 3": "https://uqload.com/embed-igurfhtbx05g.html",
        "Opción 4": "https://videobin.co/embed-vqbgv017asrr.html",
        "Opción 5": "https://www.mp4upload.com/embed-reim5bf4x5ff.html"
    },
    "12": {
        "Opción 1": "https://ok.ru/videoembed/1920293603889",
        "Opción 2": "https://www.fembed.com/v/y2zz2ce7l828kgp",
        "Opción 3": "https://uqload.com/embed-u88n8ruqsg74.html",
        "Opción 4": "https://videobin.co/embed-thh8n9hcaoin.html",
        "Opción 5": "https://www.mp4upload.com/embed-gx3d3786rsri.html"
    },
    "13": {
        "Opción 1": "https://ok.ru/videoembed/1920294062641",
        "Opción 2": "https://www.fembed.com/v/47dd7uzw1qgmr-6",
        "Opción 3": "https://uqload.com/embed-8pszt2fmabsz.html",
        "Opción 4": "https://videobin.co/embed-2yn9c1jys68z.html",
        "Opción 5": "https://www.mp4upload.com/embed-d2vrgkn54s27.html"
    }
}