{
    "1": {
        "Opción 1": "https://ok.ru/videoembed/1837174884913",
        "Opción 2": "https://www.fembed.com/v/24664b2qgkdjy0y",
        "Opción 3": "https://uqload.com/embed-vb9nwqbkxieu.html",
        "Opción 4": "https://videobin.co/embed-cr69cssu60o9.html",
        "Opción 5": "https://www.mp4upload.com/embed-7fbfrchnhsif.html"
    },
    "2": {
        "Opción 1": "https://ok.ru/videoembed/1837176195633",
        "Opción 2": "https://www.fembed.com/v/05225hld4w8pl-5",
        "Opción 3": "https://uqload.com/embed-6bi91gwsipwk.html",
        "Opción 4": "https://videobin.co/embed-imsfh3oz70mm.html"
    },
    "3": {
        "Opción 1": "https://ok.ru/videoembed/1837177309745",
        "Opción 2": "https://www.fembed.com/v/kyjjyf3jd-wdn5n",
        "Opción 3": "https://uqload.com/embed-ni9lgrybw6af.html",
        "Opción 4": "https://videobin.co/embed-x0najmldad9v.html"
    },
    "4": {
        "Opción 1": "https://ok.ru/videoembed/1837182093873",
        "Opción 2": "https://www.fembed.com/v/8p11pc8wg6mx8w7",
        "Opción 3": "https://uqload.com/embed-9fkn8f46f3vj.html",
        "Opción 4": "https://videobin.co/embed-9u8pc3tzsopd.html",
        "Opción 5": "https://www.mp4upload.com/embed-eo2b1kwbheoz.html"
    },
    "5": {
        "Opción 1": "https://ok.ru/videoembed/1837183076913",
        "Opción 2": "https://www.fembed.com/v/qy66yfewzyn7w47",
        "Opción 3": "https://uqload.com/embed-k3x9k0gsnogv.html",
        "Opción 4": "https://videobin.co/embed-a7tdcvbdky6c.html",
        "Opción 5": "https://www.mp4upload.com/embed-ol5ziy5ga3o8.html"
    },
    "6": {
        "Opción 1": "https://ok.ru/videoembed/1837183666737",
        "Opción 2": "https://www.fembed.com/v/dkjjktxw3neped-",
        "Opción 3": "https://uqload.com/embed-u7y9tc7ii8hb.html",
        "Opción 4": "https://videobin.co/embed-g89g7uezhwua.html",
        "Opción 5": "https://www.mp4upload.com/embed-aqsqxqzpthnl.html"
    },
    "7": {
        "Opción 1": "https://ok.ru/videoembed/1837185239601",
        "Opción 2": "https://www.fembed.com/v/w3113an758z8pym",
        "Opción 3": "https://uqload.com/embed-ujlctuw2x15s.html",
        "Opción 4": "https://videobin.co/embed-fuk86nveagkb.html",
        "Opción 5": "https://www.mp4upload.com/embed-isbpzn8rqoiq.html"
    },
    "8": {
        "Opción 1": "https://ok.ru/videoembed/1837186222641",
        "Opción 2": "https://www.fembed.com/v/ry77yfep7jze-my",
        "Opción 3": "https://uqload.com/embed-txf4rszq8srp.html",
        "Opción 4": "https://videobin.co/embed-e2vvi6209e80.html",
        "Opción 5": "https://www.mp4upload.com/embed-d3p3r6envx4o.html"
    },
    "9": {
        "Opción 1": "https://ok.ru/videoembed/1837197691441",
        "Opción 2": "https://www.fembed.com/v/13443ajn06zjzg-",
        "Opción 3": "https://uqload.com/embed-zhej86uxe632.html",
        "Opción 4": "https://videobin.co/embed-45c3ua80xgmn.html",
        "Opción 5": "https://www.mp4upload.com/embed-xi52azk8soro.html"
    },
    "10": {
        "Opción 1": "https://ok.ru/videoembed/1837198805553",
        "Opción 2": "https://www.fembed.com/v/-z22zfp2zwllxpk",
        "Opción 3": "https://uqload.com/embed-nkjhu34q6m5l.html",
        "Opción 4": "https://videobin.co/embed-wsem6fawoqky.html",
        "Opción 5": "https://www.mp4upload.com/embed-m2botzcx0um5.html"
    },
    "11": {
        "Opción 1": "https://ok.ru/videoembed/1837199985201",
        "Opción 2": "https://www.fembed.com/v/ry77yfep7j405xm",
        "Opción 3": "https://uqload.com/embed-ieggfoltlzjb.html",
        "Opción 4": "https://videobin.co/embed-8oleqarkuesr.html",
        "Opción 5": "https://www.mp4upload.com/embed-mqts6zvdmwjc.html"
    },
    "12": {
        "Opción 1": "https://ok.ru/videoembed/1837201099313",
        "Opción 2": "https://www.fembed.com/v/47dd7uzw-l70jpp",
        "Opción 3": "https://uqload.com/embed-a5qc4m4afsaz.html",
        "Opción 4": "https://videobin.co/embed-d2jzqu8e732x.html",
        "Opción 5": "https://www.mp4upload.com/embed-qmsb9whpauh9.html"
    }
}