{
    "1": {
        "Opción 1": "https://www.yourupload.com/embed/SgorSr8SkSjL",
        "Opción 2": "https://sbchill.com/e/w6b8l9tr36c0.html",
        "Opción 3": "https://dood.yt/e/tzeuua62yb73",
        "Opción 4": "https://www.fembed.com/v/24664b2580lw4d6",
        "Opción 5": "https://uqload.com/embed-uvq8k6cynaru.html",
        "Opción 6": "https://www.mp4upload.com/embed-5ujtmh1hlkw2.html"
    },
    "2": {
        "Opción 1": "https://www.yourupload.com/embed/YLUVA3xrjHCI",
        "Opción 2": "https://ok.ru/videoembed/4095162976927",
        "Opción 3": "https://sbchill.com/e/m93eerfbx93e.html",
        "Opción 4": "https://dood.yt/e/lbf50gbtea78",
        "Opción 5": "https://www.fembed.com/v/8p11pc8ejny2zk1",
        "Opción 6": "https://uqload.com/embed-xfrpikbioxit.html",
        "Opción 7": "https://www.mp4upload.com/embed-dur1vbgg1fk2.html"
    },
    "3": {
        "Opción 1": "https://www.yourupload.com/embed/86SgACmW6006",
        "Opción 2": "https://ok.ru/videoembed/4115952634527",
        "Opción 3": "https://sbchill.com/e/v90w2wcbmd67.html",
        "Opción 4": "https://dood.yt/e/mom015p9afwx",
        "Opción 5": "https://www.fembed.com/v/7rpprtgrd6325qj",
        "Opción 6": "https://uqload.com/embed-fzffnhl5ggsd.html"
    },
    "4": {
        "Opción 1": "https://www.yourupload.com/embed/E0S8meN33nF0",
        "Opción 2": "https://ok.ru/videoembed/4136663452319",
        "Opción 3": "https://sbchill.com/e/yfcu7p2ibkn0.html",
        "Opción 4": "https://dood.yt/e/h619a28gu75p",
        "Opción 5": "https://www.fembed.com/v/myjjyf5k51-4r60",
        "Opción 6": "https://uqload.com/embed-ffal5owdwxok.html"
    },
    "5": {
        "Opción 1": "https://www.yourupload.com/embed/tBKKKbPR51Pf",
        "Opción 2": "https://ok.ru/videoembed/4157498722975",
        "Opción 3": "https://dood.yt/e/8fi4ncwjud3b",
        "Opción 4": "https://www.fembed.com/v/47dd7uz08nz368k",
        "Opción 5": "https://uqload.com/embed-fiqxsez72vdn.html",
        "Opción 6": "https://sbhight.com/gfawk90yru8g.html"
    },
    "6": {
        "Opción 1": "https://www.yourupload.com/embed/a85QD6641pin",
        "Opción 2": "https://ok.ru/videoembed/4177811475103",
        "Opción 3": "https://sbhight.com/e/yv9xtny18179.html",
        "Opción 4": "https://dood.yt/e/94kbz2a8vtfx",
        "Opción 5": "https://www.fembed.com/v/7rpprtgr64xy8jp",
        "Opción 6": "https://www.mp4upload.com/embed-vhk3sjrhsoug.html"
    },
    "7": {
        "Opción 1": "https://www.yourupload.com/embed/e0Lw71mk4wES",
        "Opción 2": "https://ok.ru/videoembed/4199320849055",
        "Opción 3": "https://sbbrisk.com/e/aans7g2lh4zq.html",
        "Opción 4": "https://dood.yt/e/bej022scsgaz",
        "Opción 5": "https://www.fembed.com/v/dkjjktx05en4qjl"
    },
    "8": {
        "Opción 1": "https://www.yourupload.com/embed/WdT76pM20a7F",
        "Opción 2": "https://ok.ru/videoembed/4223126932127",
        "Opción 3": "https://www.fembed.com/v/-z22zfpqezkqx6r",
        "Opción 4": "https://sbbrisk.com/e/1mdy3fhsttzv.html",
        "Opción 5": "https://www.mp4upload.com/embed-qy62nazvbdyv.html"
    },
    "9": {
        "Opción 1": "https://www.yourupload.com/embed/Ioh0NANw45Y6",
        "Opción 2": "https://ok.ru/videoembed/4251652786847",
        "Opción 3": "https://www.fembed.com/v/j-jj-adlrmp34gy",
        "Opción 4": "https://sbbrisk.com/e/qjyvzjyne56d.html",
        "Opción 5": "https://dood.yt/e/eehid3ex22yr"
    },
    "10": {
        "Opción 1": "https://www.yourupload.com/embed/ph7W0D1aybk5",
        "Opción 2": "https://ok.ru/videoembed/4304500492959",
        "Opción 3": "https://filemoon.sx/e/nepzflb9mrfc",
        "Opción 4": "https://www.fembed.com/v/5d00dcd5556gnw-",
        "Opción 5": "https://sbbrisk.com/e/b2lybghhn4qg.html",
        "Opción 6": "https://dood.yt/e/gya6ax0dgjtb"
    },
    "11": {
        "Opción 1": "https://www.yourupload.com/embed/TrBdQ4MeND1e",
        "Opción 2": "https://www.fembed.com/v/py44yf7ldmy-753",
        "Opción 3": "https://sbbrisk.com/e/uqtez5x84xz7.html",
        "Opción 4": "https://dood.yt/e/ucazus7y84h5",
        "Opción 5": "https://www.mp4upload.com/embed-4hm5e53y00mp.html"
    },
    "12": {
        "Opción 1": "https://www.yourupload.com/embed/u2m20PW1d75I",
        "Opción 2": "https://ok.ru/videoembed/4404101319327",
        "Opción 3": "https://www.fembed.com/v/x4kk4b1nygjjpj2",
        "Opción 4": "https://sbface.com/e/lx3v2yrds0cg.html",
        "Opción 5": "https://dood.yt/e/kuqa0vqrgp5m",
        "Opción 6": "https://www.mp4upload.com/embed-f200f4uybt0t.html"
    }
}