{
    "1": {
        "Opción 1": "https://ok.ru/videoembed/2664189004458",
        "Opción 2": "https://www.fembed.com/v/36776am86l520kn",
        "Opción 3": "https://repro.monoschinos2.com/aqua/sv?url=https://sendvid.com/g5khg31g",
        "Opción 4": "https://videobin.co/embed-bsqgbvxbl35q.html"
    },
    "2": {
        "Opción 1": "https://ok.ru/videoembed/2664190642858",
        "Opción 2": "https://www.fembed.com/v/kyjjyf31jzpqkk1",
        "Opción 3": "https://repro.monoschinos2.com/aqua/sv?url=https://sendvid.com/8gttx5ap",
        "Opción 4": "https://videobin.co/embed-6q0gd850sti4.html",
        "Opción 5": "https://www.mp4upload.com/embed-bchkj8s1epxo.html"
    },
    "3": {
        "Opción 1": "https://ok.ru/videoembed/2664192150186",
        "Opción 2": "https://www.fembed.com/v/y2zz2ce176y6jr8",
        "Opción 3": "https://videobin.co/embed-5faza7uo0oox.html",
        "Opción 4": "https://www.mp4upload.com/embed-94fciih4ny8y.html"
    },
    "4": {
        "Opción 1": "https://ok.ru/videoembed/2691299019434",
        "Opción 2": "https://www.fembed.com/v/-z22zfpl6073m6n",
        "Opción 3": "https://videobin.co/embed-yxv7r5qe5u51.html",
        "Opción 4": "https://www.mp4upload.com/embed-47lgqi983q9h.html"
    },
    "5": {
        "Opción 1": "https://ok.ru/videoembed/2694592596650",
        "Opción 2": "https://www.fembed.com/v/lnjjnfnp0p63yxp",
        "Opción 3": "https://videobin.co/embed-h9a5lpgd30st.html",
        "Opción 4": "https://www.mp4upload.com/embed-btvybz7ajkd9.html"
    },
    "6": {
        "Opción 1": "https://ok.ru/videoembed/2709821393578",
        "Opción 2": "https://www.fembed.com/v/gqjjqc-pe8d85rw",
        "Opción 3": "https://videobin.co/embed-eka9ehmbvv7j.html",
        "Opción 4": "https://www.mp4upload.com/embed-s3zc0rh4ob7a.html"
    },
    "7": {
        "Opción 1": "https://ok.ru/videoembed/2729740536490",
        "Opción 2": "https://www.fembed.com/v/qy66yfe303jep74",
        "Opción 3": "https://videobin.co/embed-vftyd7h2wvl2.html",
        "Opción 4": "https://www.mp4upload.com/embed-29hjc2t7jspt.html"
    },
    "8": {
        "Opción 1": "https://ok.ru/videoembed/2764642192042",
        "Opción 2": "https://www.fembed.com/v/qy66yfe3l5jgx-0",
        "Opción 3": "https://uqload.com/embed-jgero9z052sq.html",
        "Opción 4": "https://videobin.co/embed-1zl0dfv6l3sw.html",
        "Opción 5": "https://www.mp4upload.com/embed-tq0em5i6k1bs.html"
    },
    "9": {
        "Opción 1": "https://ok.ru/videoembed/2764644551338",
        "Opción 2": "https://www.fembed.com/v/60rr0t047r8lmee",
        "Opción 3": "https://uqload.com/embed-xyfh7zym7r2x.html",
        "Opción 4": "https://videobin.co/embed-r8ce4icue258.html",
        "Opción 5": "https://www.mp4upload.com/embed-2n2kkt5dr3dw.html"
    },
    "10": {
        "Opción 1": "https://ok.ru/videoembed/2799171406506",
        "Opción 2": "https://www.fembed.com/v/lnjjnfnjq6n5n8w",
        "Opción 3": "https://uqload.com/embed-z4oi82vdf01n.html",
        "Opción 4": "https://videobin.co/embed-8nwd6w0qsx1t.html",
        "Opción 5": "https://www.mp4upload.com/embed-1jpm5wittame.html"
    }
}